qimchi/__init__.py
qimchi/__main__.py
qimchi/app.py
qimchi/assets/android-chrome-192x192.png
qimchi/assets/android-chrome-512x512.png
qimchi/assets/apple-touch-icon.png
qimchi/assets/css/styles.css
qimchi/assets/favicon-16x16.png
qimchi/assets/favicon-32x32.png
qimchi/assets/favicon.ico
qimchi/assets/logos/SQUAD Logo.webp
qimchi/assets/logos/qimchi-logo.png
qimchi/assets/site.webmanifest
qimchi/components/__init__.py
qimchi/components/appearance.py
qimchi/components/data/__init__.py
qimchi/components/data/base.py
qimchi/components/data/squad/__init__.py
qimchi/components/data/squad/datasets.py
qimchi/components/figures.py
qimchi/components/filters/__init__.py
qimchi/components/filters/filters.py
qimchi/components/metadata.py
qimchi/components/navbar.py
qimchi/components/notes.py
qimchi/components/plot_callbacks.py
qimchi/components/plot_elements.py
qimchi/components/plot_filters.py
qimchi/components/plots.py
qimchi/components/selector.py
qimchi/components/utils/__init__.py
qimchi/components/utils/common.py
qimchi/logger.py
qimchi/pages/__init__.py
qimchi/pages/home.py
qimchi/state.py
qimchi-0.0.22.dist-info/LICENSE
qimchi-0.0.22.dist-info/METADATA
qimchi-0.0.22.dist-info/WHEEL
qimchi-0.0.22.dist-info/RECORD
